LICENSE
README.rst
setup.py
dnalib/__init__.py
dnalib.egg-info/PKG-INFO
dnalib.egg-info/SOURCES.txt
dnalib.egg-info/dependency_links.txt
dnalib.egg-info/requires.txt
dnalib.egg-info/top_level.txt
dnalib/blockchain/__init__.py
dnalib/blockchain/block.py
dnalib/blockchain/blockbucket.py
dnalib/blockchain/blockchain.py
dnalib/blockchain/key.py
dnalib/core/__init__.py
dnalib/core/createtable.py
dnalib/core/createview.py
dnalib/core/ddl.py
dnalib/core/field.py
dnalib/core/table.py
dnalib/core/tablecomment.py
dnalib/custom/__init__.py
dnalib/custom/ymlloader.py
dnalib/dataquality/__init__.py
dnalib/dataquality/greatexpectations.py
dnalib/ftp/__init__.py
dnalib/ftp/ftp.py
dnalib/loaders/__init__.py
dnalib/loaders/firebaseloader.py
dnalib/loaders/loader.py
dnalib/loaders/loaderfactory.py
dnalib/loaders/sqlparquetlandingloader.py
dnalib/log/__init__.py
dnalib/log/log.py
dnalib/sftp/__init__.py
dnalib/sftp/sftp.py
dnalib/tables/__init__.py
dnalib/tables/bronzetable.py
dnalib/tables/dynamictable.py
dnalib/tables/querytable.py
dnalib/tables/silvertable.py
dnalib/tables/tables.py
dnalib/utils/__init__.py
dnalib/utils/fileutils.py
dnalib/utils/landingzoneutils.py
dnalib/utils/tableutils.py
dnalib/utils/utils.py
dnalib/writer/__init__.py
dnalib/writer/tablewriter.py