Metadata-Version: 2.1
Name: dnalib
Version: 0.1.34
Summary: A Python library for fast development of Data Engineering ETL using spark.
Author: Charles Gobber
Author-email: charles26f@gmail.com
License: Apache-2
License-File: LICENSE
